pytimeparse2.py
pytimeparse2-1.7.1.dist-info/METADATA
pytimeparse2-1.7.1.dist-info/RECORD
pytimeparse2-1.7.1.dist-info/WHEEL
pytimeparse2-1.7.1.dist-info/top_level.txt
