Metadata-Version: 2.1
Name: pytimeparse2
Version: 1.7.1
Summary: Time expression parser.
Home-page: https://github.com/onegreyonewhite/pytimeparse2
Author: Sergey Klyuykov
Author-email: onegreyonewhite@mail.ru
License: MIT
Project-URL: Issue Tracker, https://github.com/onegreyonewhite/pytimeparse2/-/issues
Project-URL: Source Code, https://github.com/onegreyonewhite/pytimeparse2.git
Project-URL: Releases, https://pypi.org/project/pytimeparse2/#history
Keywords: parsing,time,timeparsing,text
Platform: UNKNOWN
Classifier: Development Status :: 5 - Production/Stable
Classifier: Intended Audience :: Developers
Classifier: License :: OSI Approved :: MIT License
Classifier: Programming Language :: Python
Classifier: Programming Language :: Python :: 3
Classifier: Programming Language :: Python :: 3 :: Only
Classifier: Programming Language :: Python :: 3.6
Classifier: Programming Language :: Python :: 3.7
Classifier: Programming Language :: Python :: 3.8
Classifier: Programming Language :: Python :: 3.9
Classifier: Programming Language :: Python :: 3.10
Classifier: Programming Language :: Python :: 3.11
Classifier: Programming Language :: Python :: Implementation :: CPython
Classifier: Topic :: Software Development :: Libraries
Classifier: Topic :: Software Development :: Libraries :: Python Modules
Classifier: Topic :: Text Processing
Classifier: Topic :: Utilities
Requires-Python: >=3.6
Provides-Extra: dateutil
License-File: LICENSE.rst
